LICENSE
README.md
pyproject.toml
appicongen/__init__.py
appicongen/__main__.py
appicongen/imaging.py
appicongen/size.py
appicongen/utils.py
appicongen.egg-info/PKG-INFO
appicongen.egg-info/SOURCES.txt
appicongen.egg-info/dependency_links.txt
appicongen.egg-info/entry_points.txt
appicongen.egg-info/requires.txt
appicongen.egg-info/top_level.txt