Metadata-Version: 2.1
Name: appicongen
Version: 0.1.9
Summary: CLI tool for generating app icon sets for macOS, iOS and watchOS projects
Project-URL: Homepage, https://github.com/fwcd/appicongen
Project-URL: Repository, https://github.com/fwcd/appicongen
Classifier: Topic :: Utilities
License-File: LICENSE
Requires-Dist: Pillow<10,>=9.0.1
Requires-Dist: numpy<2,>=1.23
